plottwist/__init__.py
plottwist/config.json
plottwist/launcher.json
plottwist/menu.json
plottwist/shelf.json
plottwist/updater.json
plottwist/version.json
plottwist/core/__init__.py
plottwist/core/project.py
plottwist/launcher/__init__.py
plottwist/launcher/launcher.py
plottwist/launcher/tray.py
plottwist/launcher/updater.py
plottwist/pipeline/__init__.py
plottwist/pipeline/externals/__init__.py
plottwist/resources/icons/plottwist.png
plottwist/resources/icons/plottwist_icon.png
plottwist/resources/icons/plottwist_shelf.png
plottwist/resources/icons/color/artella.png
plottwist/resources/icons/color/documentation.png
plottwist/resources/icons/color/drive.png
plottwist/resources/icons/color/kitsu.png
plottwist/resources/icons/color/message.png
plottwist/resources/images/splash1.png
plottwist/resources/images/splash2.png
plottwist/resources/images/splash3.png
plottwist/resources/images/splash4.png
plottwist/resources/images/splash5.png
plottwist/resources/images/splash6.png
plottwist/resources/images/splash7.png
plottwist-0.0.1.dist-info/LICENSE
plottwist-0.0.1.dist-info/METADATA
plottwist-0.0.1.dist-info/WHEEL
plottwist-0.0.1.dist-info/top_level.txt
plottwist-0.0.1.dist-info/RECORD
