Metadata-Version: 2.1
Name: plottwist
Version: 0.0.1
Summary: Artella based pipeline framework for Plot Twist Short Film
Home-page: UNKNOWN
Author: Tomas Poveda
Author-email: tpovedatd@gmail.com
License: MIT
Platform: UNKNOWN
Requires-Dist: artellalauncher
Provides-Extra: dev
Requires-Dist: wheel ; extra == 'dev'
Provides-Extra: test
Requires-Dist: pytest ; extra == 'test'
